flask_dynamodb_sessions/__init__.py
flask_dynamodb_sessions-0.1.7.dist-info/AUTHORS.rst
flask_dynamodb_sessions-0.1.7.dist-info/LICENSE
flask_dynamodb_sessions-0.1.7.dist-info/METADATA
flask_dynamodb_sessions-0.1.7.dist-info/WHEEL
flask_dynamodb_sessions-0.1.7.dist-info/top_level.txt
flask_dynamodb_sessions-0.1.7.dist-info/RECORD
