Metadata-Version: 2.1
Name: flask-dynamodb-sessions
Version: 0.1.7
Summary: Server side sessions in Flask using AWS DynamoDB table as a data store
Home-page: https://github.com/ibejohn818/flask-dynamodb-sessions
Author: John Hardy
Author-email: john@johnchardy.com
License: MIT license
Keywords: flask-dynamodb-sessions
Platform: UNKNOWN
Classifier: Development Status :: 2 - Pre-Alpha
Classifier: Intended Audience :: Developers
Classifier: License :: OSI Approved :: MIT License
Classifier: Natural Language :: English
Classifier: Programming Language :: Python :: 2
Classifier: Programming Language :: Python :: 2.7
Classifier: Programming Language :: Python :: 3
Classifier: Programming Language :: Python :: 3.4
Classifier: Programming Language :: Python :: 3.5
Classifier: Programming Language :: Python :: 3.6
Classifier: Programming Language :: Python :: 3.7
Requires-Dist: boto3
